README.rst
setup.py
multicraft_backup/__init__.py
multicraft_backup/__main__.py
multicraft_backup/backup.py
multicraft_backup/server.py
multicraft_backup.egg-info/PKG-INFO
multicraft_backup.egg-info/SOURCES.txt
multicraft_backup.egg-info/dependency_links.txt
multicraft_backup.egg-info/requires.txt
multicraft_backup.egg-info/top_level.txt
tests/__init__.py
tests/test_sample.py