Metadata-Version: 1.1
Name: multicraft-backup
Version: 0.3.0
Summary: Backs up your Minecraft servers from hosts that use Multicraft
Home-page: https://github.com/bmintz/multicraft-backup
Author: Benjamin Mintz
Author-email: bmintz@protonmail.com
License: UNKNOWN
Platform: UNKNOWN
Classifier: License :: OSI Approved :: GNU General Public License v2 (GPLv2)
Classifier: Development Status :: 2 - Pre-Alpha
Classifier: Programming Language :: Python
Classifier: Programming Language :: Python :: 3
Classifier: Programming Language :: Python :: 3.4
Classifier: Programming Language :: Python :: 3.5
